github_mcp/__init__.py
github_mcp/__main__.py
github_mcp/cli.py
github_mcp/deno.json
github_mcp/deno_runtime.py
github_mcp/server.py
github_mcp/auth/github_app.py
github_mcp/deno_executor/README.md
github_mcp/deno_executor/code-validator.test.ts
github_mcp/deno_executor/code-validator.ts
github_mcp/deno_executor/error-codes.ts
github_mcp/deno_executor/error-handling.test.ts
github_mcp/deno_executor/mod.ts
github_mcp/deno_executor/test_runtime.ts
github_mcp/deno_executor/tool-definitions.ts
github_mcp/models/__init__.py
github_mcp/models/enums.py
github_mcp/models/inputs.py
github_mcp/servers/client-deno.ts
github_mcp/servers/client.ts
github_mcp/servers/package-lock.json
github_mcp/servers/package.json
github_mcp/servers/test-connection.ts
github_mcp/servers/test-error-handling.ts
github_mcp/servers/test-params.ts
github_mcp/servers/test-simple.ts
github_mcp/servers/test-tool-call.ts
github_mcp/servers/tsconfig.json
github_mcp/servers/github/index.ts
github_mcp/servers/github/advisor/github-suggest-workflow.ts
github_mcp/servers/github/advisor/index.ts
github_mcp/servers/github/commits/github-list-commits.ts
github_mcp/servers/github/commits/index.ts
github_mcp/servers/github/files/github-batch-file-operations.ts
github_mcp/servers/github/files/github-create-file.ts
github_mcp/servers/github/files/github-delete-file.ts
github_mcp/servers/github/files/github-get-file-content.ts
github_mcp/servers/github/files/github-update-file.ts
github_mcp/servers/github/files/index.ts
github_mcp/servers/github/issues/github-create-issue.ts
github_mcp/servers/github/issues/github-list-issues.ts
github_mcp/servers/github/issues/github-search-issues.ts
github_mcp/servers/github/issues/github-update-issue.ts
github_mcp/servers/github/issues/index.ts
github_mcp/servers/github/license/github-license-info.ts
github_mcp/servers/github/license/index.ts
github_mcp/servers/github/pulls/github-close-pull-request.ts
github_mcp/servers/github/pulls/github-create-pr-review.ts
github_mcp_server-2.5.7.dist-info/licenses/LICENSE
github_mcp_server-2.5.7.dist-info/licenses/LICENSE-COMMERCIAL
github_mcp_server-2.5.7.dist-info/METADATA
github_mcp_server-2.5.7.dist-info/WHEEL
github_mcp_server-2.5.7.dist-info/entry_points.txt
github_mcp_server-2.5.7.dist-info/top_level.txt
github_mcp_server-2.5.7.dist-info/RECORD
