Metadata-Version: 2.4
Name: github-mcp-server
Version: 2.5.7
Summary: The most AI-optimized GitHub MCP server: 112 tools, code-first architecture (98% token reduction), compact responses (80-97% smaller). Built for efficient AI development.
Author-email: MCP Labs <licensing@mcplabs.co.uk>
License-Expression: AGPL-3.0-or-later
Project-URL: Homepage, https://github.com/crypto-ninja/mcp-server-for-Github
Project-URL: Documentation, https://github.com/crypto-ninja/mcp-server-for-Github#readme
Project-URL: Repository, https://github.com/crypto-ninja/mcp-server-for-Github
Project-URL: Issues, https://github.com/crypto-ninja/mcp-server-for-Github/issues
Project-URL: Changelog, https://github.com/crypto-ninja/mcp-server-for-Github/blob/main/CHANGELOG.md
Keywords: mcp,model-context-protocol,github,api,ai,assistant,claude
Classifier: Development Status :: 5 - Production/Stable
Classifier: Intended Audience :: Developers
Classifier: Topic :: Software Development :: Libraries :: Python Modules
Classifier: Programming Language :: Python :: 3
Classifier: Programming Language :: Python :: 3.10
Classifier: Programming Language :: Python :: 3.11
Classifier: Programming Language :: Python :: 3.12
Classifier: Operating System :: OS Independent
Requires-Python: >=3.10
License-File: LICENSE
License-File: LICENSE-COMMERCIAL
Requires-Dist: mcp<2.0.0,>=1.0.0
Requires-Dist: httpx>=0.25.0
Requires-Dist: pydantic>=2.0.0
Requires-Dist: PyJWT>=2.8.0
Requires-Dist: click>=8.0.0
Provides-Extra: dev
Requires-Dist: pytest>=7.0; extra == "dev"
Requires-Dist: pytest-asyncio>=0.21.0; extra == "dev"
Requires-Dist: pytest-cov>=4.0; extra == "dev"
Requires-Dist: pytest-httpx>=0.21.0; extra == "dev"
Requires-Dist: ruff>=0.1.0; extra == "dev"
Requires-Dist: mypy>=1.0.0; extra == "dev"
Requires-Dist: pip-audit>=2.6.0; extra == "dev"
Requires-Dist: python-dotenv>=1.0.0; extra == "dev"
Dynamic: license-file
